unsplash_wrapper/__init__.py
unsplash_wrapper/client.py
unsplash_wrapper/exceptions.py
unsplash_wrapper/search/__init__.py
unsplash_wrapper/search/builder.py
unsplash_wrapper/search/models.py
unsplash_wrapper/utils/decorators.py
unsplash_wrapper/utils/logging.py
unsplash_wrapper-0.2.0.dist-info/METADATA
unsplash_wrapper-0.2.0.dist-info/WHEEL
unsplash_wrapper-0.2.0.dist-info/licenses/LICENSE
unsplash_wrapper-0.2.0.dist-info/RECORD
