Metadata-Version: 2.4
Name: unsplash-wrapper
Version: 0.2.0
Summary: Python client for the Unsplash API
License-File: LICENSE
Requires-Python: >=3.13
Requires-Dist: httpx>=0.28.1
Requires-Dist: pydantic>=2.12.3
Requires-Dist: python-dotenv>=1.2.1
